ramonak/__about__.py
ramonak/__init__.py
ramonak/exceptions.py
ramonak/punct.py
ramonak/rules.py
ramonak/stopwords.py
ramonak/tokenize.py
ramonak/packages/__init__.py
ramonak/packages/_utils.py
ramonak/packages/actions.py
ramonak/packages/herbarium/@alerus/flexistat_data.toml
ramonak/packages/herbarium/@alerus/stopwords.toml
ramonak/packages/herbarium/@bnkorpus/grammar_db.toml
ramonak/packages/herbarium/@poritski/yabc.toml
ramonak/stemmer/__init__.py
ramonak/stemmer/base.py
ramonak/stemmer/flexistat.py
ramonak-0.5.0.dist-info/METADATA
ramonak-0.5.0.dist-info/WHEEL
ramonak-0.5.0.dist-info/licenses/LICENSE
ramonak-0.5.0.dist-info/RECORD
