Metadata-Version: 2.4
Name: ramonak
Version: 0.5.0
Summary: Універсальная бібліятэка па працы з тэкстам на беларускай мове для Python
Project-URL: Documentation, https://github.com/alex-rusakevich/ramonak#readme
Project-URL: Issues, https://github.com/alex-rusakevich/ramonak/issues
Project-URL: Source, https://github.com/alex-rusakevich/ramonak
Author-email: Alexander Rusakevich <mr.alexander.rusakevich@gmail.com>
License-Expression: LGPL-3.0
License-File: LICENSE
Classifier: Development Status :: 4 - Beta
Classifier: Programming Language :: Python
Classifier: Programming Language :: Python :: 3.11
Classifier: Programming Language :: Python :: 3.12
Classifier: Programming Language :: Python :: 3.13
Classifier: Programming Language :: Python :: Implementation :: CPython
Requires-Python: >=3.11
Requires-Dist: lxml>=5.3.0
Requires-Dist: python-dotenv>=1.0.1
Requires-Dist: requests>=2.32.3
Requires-Dist: tqdm>=4.67.1
